amapy_db/__init__.py
amapy_db/assets_db.py
amapy_db/db.py
amapy_db/file_db.py
amapy_db/manifest_db.py
amapy_db/repo_db.py
amapy_db/states_db.py
amapy_db/store_db.py
amapy_db/store_file_db.py
amapy_db/tests/__init__.py
amapy_db/tests/test_assets_db.py
amapy_db/tests/test_db.py
amapy_db/tests/test_file_db.py
amapy_db/tests/test_manifest_db.py
amapy_db/tests/test_states_db.py
amapy_db-1.0.1.dist-info/METADATA
amapy_db-1.0.1.dist-info/WHEEL
amapy_db-1.0.1.dist-info/top_level.txt
amapy_db-1.0.1.dist-info/RECORD
