Metadata-Version: 2.1
Name: amapy-db
Version: 1.0.1
Summary: The Database plugin for ama project.
License: Copyright (c) 2024 Roche Diagnostics Computation Science & Informatics
Requires-Python: <3.11,>=3.10
Requires-Dist: amapy-pluggy==1.*
Requires-Dist: amapy-utils==1.*
